hardnested.cp310-win_amd64.pyd
nested.cp310-win_amd64.pyd
FlipperNested/bridge.py
FlipperNested/cli.py
FlipperNested/main.py
FlipperNested/__init__.py
FlipperNested/__main__.py
FlipperNested/proto/flipper_pb2.py
FlipperNested/proto/storage_pb2.py
FlipperNested/proto/__init__.py
FlipperNested-2.3.5.data/headers/ansi.h
FlipperNested-2.3.5.data/headers/bucketsort.h
FlipperNested-2.3.5.data/headers/cmdhfmfhard.h
FlipperNested-2.3.5.data/headers/common.h
FlipperNested-2.3.5.data/headers/commonutil.h
FlipperNested-2.3.5.data/headers/crapto1.h
FlipperNested-2.3.5.data/headers/emojis.h
FlipperNested-2.3.5.data/headers/emojis_alt.h
FlipperNested-2.3.5.data/headers/hardnested_benchmark_data.h
FlipperNested-2.3.5.data/headers/hardnested_bf_core.h
FlipperNested-2.3.5.data/headers/hardnested_bitarray_core.h
FlipperNested-2.3.5.data/headers/hardnested_bruteforce.h
FlipperNested-2.3.5.data/headers/library.h
FlipperNested-2.3.5.data/headers/parity.h
FlipperNested-2.3.5.data/headers/progress.h
FlipperNested-2.3.5.data/headers/tables.h
FlipperNested-2.3.5.data/headers/ui.h
FlipperNested-2.3.5.data/headers/util.h
FlipperNested-2.3.5.data/headers/util_posix.h
FlipperNested-2.3.5.data/platlib/lzma-64fe96bde4d8406725578ee01e39e4ac.dll
FlipperNested-2.3.5.data/platlib/msvcr100-d8ca233d76ac26e36dc62c29d9b9f460.dll
FlipperNested-2.3.5.data/platlib/pthreadVC2-39e0a803b0b926a920408465a2dbeedd.dll
FlipperNested-2.3.5.dist-info/DELVEWHEEL
FlipperNested-2.3.5.dist-info/entry_points.txt
FlipperNested-2.3.5.dist-info/LICENSE.md
FlipperNested-2.3.5.dist-info/METADATA
FlipperNested-2.3.5.dist-info/RECORD
FlipperNested-2.3.5.dist-info/top_level.txt
FlipperNested-2.3.5.dist-info/WHEEL
