Metadata-Version: 2.1
Name: FlipperNested
Version: 2.3.5
Summary: Recover keys from collected nonces
Home-page: https://github.com/AloneLiberty/FlipperNestedRecovery
Author: AloneLiberty
Classifier: Programming Language :: Python :: 3.8
Classifier: Programming Language :: Python :: 3.9
Classifier: Programming Language :: Python :: 3.10
Classifier: Programming Language :: Python :: 3.11
Classifier: Programming Language :: Python :: 3.12
Classifier: License :: OSI Approved :: GNU General Public License v3 (GPLv3)
Classifier: Operating System :: MacOS
Classifier: Operating System :: POSIX :: Linux
Classifier: Operating System :: Microsoft :: Windows
Requires-Python: >=3.8
License-File: LICENSE.md
Requires-Dist: protobuf (>4)
Requires-Dist: pyserial
